{
  "notes": [
    {
      "id": 1,
      "content": "custom-hooks are awesome!"
    },
    {
      "id": 2,
      "content": "best feature ever <3"
    },
    {
      "content": "Hello World",
      "id": 3
    },
    {
      "content": "hi",
      "id": 4
    },
    {
      "content": "sad",
      "id": 5
    },
    {
      "content": "Yes?",
      "id": 6
    },
    {
      "content": "HelloWorld",
      "id": 7
    },
    {
      "content": "asdasds",
      "id": 8
    },
    {
      "content": "asdasds",
      "id": 9
    },
    {
      "content": "asdasdasds",
      "id": 10
    }
  ],
  "persons": [
    {
      "id": 1,
      "name": "mluukkai",
      "number": "040-5483923"
    },
    {
      "id": 2,
      "name": "hellas",
      "number": "012-123123"
    },
    {
      "name": "Hi dad",
      "number": "123912123",
      "id": 3
    },
    {
      "name": "ho",
      "number": "hoho",
      "id": 4
    },
    {
      "name": "asdad",
      "number": "asda",
      "id": 5
    },
    {
      "name": "Hello",
      "number": "1234",
      "id": 6
    },
    {
      "name": "Brah",
      "number": "You sucks",
      "id": 7
    }
  ]
}